{"3":{"title":"GEMPIC.jl Documentation","pagetitle":"GEMPIC.jl Documentation","ref":"/gempic/dev/#GEMPIC.jl-Documentation"},"6":{"title":"Contents","pagetitle":"Contents","ref":"/gempic/dev/contents/#Contents"},"7":{"title":"Index","pagetitle":"Contents","ref":"/gempic/dev/contents/#Index"},"10":{"title":"Diagnostics","pagetitle":"Diagnostics","ref":"/gempic/dev/diagnostics/#Diagnostics"},"11":{"title":"GEMPIC.TimeHistoryDiagnostics","pagetitle":"Diagnostics","ref":"/gempic/dev/diagnostics/#GEMPIC.TimeHistoryDiagnostics"},"12":{"title":"GEMPIC.eval_derivative_spline","pagetitle":"Diagnostics","ref":"/gempic/dev/diagnostics/#GEMPIC.eval_derivative_spline-NTuple{6, Any}"},"13":{"title":"GEMPIC.evaluate","pagetitle":"Diagnostics","ref":"/gempic/dev/diagnostics/#GEMPIC.evaluate-Tuple{ParticleMeshCoupling1D, AbstractArray, AbstractArray}"},"14":{"title":"GEMPIC.pic_diagnostics_hpi","pagetitle":"Diagnostics","ref":"/gempic/dev/diagnostics/#GEMPIC.pic_diagnostics_hpi-Tuple{Any, Any, Any}"},"15":{"title":"GEMPIC.pic_diagnostics_poynting","pagetitle":"Diagnostics","ref":"/gempic/dev/diagnostics/#GEMPIC.pic_diagnostics_poynting-NTuple{4, Any}"},"16":{"title":"GEMPIC.pic_diagnostics_transfer","pagetitle":"Diagnostics","ref":"/gempic/dev/diagnostics/#GEMPIC.pic_diagnostics_transfer-Tuple{ParticleGroup{1, 2}, Any, Any, Any}"},"17":{"title":"GEMPIC.pic_diagnostics_vvb","pagetitle":"Diagnostics","ref":"/gempic/dev/diagnostics/#GEMPIC.pic_diagnostics_vvb-Tuple{Any, Any, Any}"},"18":{"title":"GEMPIC.solve_poisson!","pagetitle":"Diagnostics","ref":"/gempic/dev/diagnostics/#GEMPIC.solve_poisson!-Tuple{Vector{Float64}, GEMPIC.AbstractParticleGroup, GEMPIC.AbstractParticleMeshCoupling, Maxwell1DFEM, Vector{Float64}}"},"19":{"title":"GEMPIC.write_step!","pagetitle":"Diagnostics","ref":"/gempic/dev/diagnostics/#GEMPIC.write_step!-Tuple{TimeHistoryDiagnostics, Vararg{Any, 6}}"},"22":{"title":"Distributions","pagetitle":"Distributions","ref":"/gempic/dev/distributions/#Distributions"},"23":{"title":"GEMPIC.CosGaussianParams","pagetitle":"Distributions","ref":"/gempic/dev/distributions/#GEMPIC.CosGaussianParams"},"24":{"title":"GEMPIC.CosSumGaussian","pagetitle":"Distributions","ref":"/gempic/dev/distributions/#GEMPIC.CosSumGaussian"},"25":{"title":"GEMPIC.SumCosGaussian","pagetitle":"Distributions","ref":"/gempic/dev/distributions/#GEMPIC.SumCosGaussian"},"26":{"title":"GEMPIC.eval_v_density","pagetitle":"Distributions","ref":"/gempic/dev/distributions/#GEMPIC.eval_v_density-Tuple{GEMPIC.AbstractCosGaussian, Union{Float64, Vector{Float64}}}"},"27":{"title":"GEMPIC.eval_x_density","pagetitle":"Distributions","ref":"/gempic/dev/distributions/#GEMPIC.eval_x_density-Tuple{SumCosGaussian, Union{Float64, Vector{Float64}}}"},"30":{"title":"Hamiltonian splitting","pagetitle":"Hamiltonian splitting","ref":"/gempic/dev/hamiltonian_splitting/#Hamiltonian-splitting"},"31":{"title":"GEMPIC.HamiltonianSplitting","pagetitle":"Hamiltonian splitting","ref":"/gempic/dev/hamiltonian_splitting/#GEMPIC.HamiltonianSplitting"},"32":{"title":"GEMPIC.lie_splitting!","pagetitle":"Hamiltonian splitting","ref":"/gempic/dev/hamiltonian_splitting/#GEMPIC.lie_splitting!-Tuple{HamiltonianSplitting, Float64, Int64}"},"33":{"title":"GEMPIC.lie_splitting_back!","pagetitle":"Hamiltonian splitting","ref":"/gempic/dev/hamiltonian_splitting/#GEMPIC.lie_splitting_back!-Tuple{HamiltonianSplitting, Float64, Int64}"},"34":{"title":"GEMPIC.strang_splitting!","pagetitle":"Hamiltonian splitting","ref":"/gempic/dev/hamiltonian_splitting/#GEMPIC.strang_splitting!-Tuple{HamiltonianSplitting, Float64, Int64}"},"37":{"title":"Hamiltonian splitting Boris","pagetitle":"Hamiltonian splitting Boris","ref":"/gempic/dev/hamiltonian_splitting_boris/#Hamiltonian-splitting-Boris"},"38":{"title":"GEMPIC.HamiltonianSplittingBoris","pagetitle":"Hamiltonian splitting Boris","ref":"/gempic/dev/hamiltonian_splitting_boris/#GEMPIC.HamiltonianSplittingBoris"},"39":{"title":"GEMPIC.push_v_bpart!","pagetitle":"Hamiltonian splitting Boris","ref":"/gempic/dev/hamiltonian_splitting_boris/#GEMPIC.push_v_bpart!-Tuple{HamiltonianSplittingBoris, Float64}"},"40":{"title":"GEMPIC.push_v_epart!","pagetitle":"Hamiltonian splitting Boris","ref":"/gempic/dev/hamiltonian_splitting_boris/#GEMPIC.push_v_epart!-Tuple{Any, Any}"},"41":{"title":"GEMPIC.push_x_accumulate_j!","pagetitle":"Hamiltonian splitting Boris","ref":"/gempic/dev/hamiltonian_splitting_boris/#GEMPIC.push_x_accumulate_j!-Tuple{Any, Any}"},"42":{"title":"GEMPIC.staggering!","pagetitle":"Hamiltonian splitting Boris","ref":"/gempic/dev/hamiltonian_splitting_boris/#GEMPIC.staggering!-Tuple{Any, Any}"},"43":{"title":"GEMPIC.strang_splitting!","pagetitle":"Hamiltonian splitting Boris","ref":"/gempic/dev/hamiltonian_splitting_boris/#GEMPIC.strang_splitting!-Tuple{HamiltonianSplittingBoris, Float64, Int64}"},"46":{"title":"Splines","pagetitle":"Splines","ref":"/gempic/dev/low_level_bsplines/#Splines"},"47":{"title":"GEMPIC.eval_uniform_periodic_spline_curve","pagetitle":"Splines","ref":"/gempic/dev/low_level_bsplines/#GEMPIC.eval_uniform_periodic_spline_curve-Tuple{Int64, Vector{Float64}}"},"48":{"title":"GEMPIC.uniform_bsplines_eval_basis","pagetitle":"Splines","ref":"/gempic/dev/low_level_bsplines/#GEMPIC.uniform_bsplines_eval_basis-Tuple{Int64, Float64}"},"51":{"title":"Maxwell solver","pagetitle":"Maxwell solver","ref":"/gempic/dev/maxwell_solver/#Maxwell-solver"},"52":{"title":"GEMPIC.Maxwell1DFEM","pagetitle":"Maxwell solver","ref":"/gempic/dev/maxwell_solver/#GEMPIC.Maxwell1DFEM"},"53":{"title":"GEMPIC.compute_b_from_e!","pagetitle":"Maxwell solver","ref":"/gempic/dev/maxwell_solver/#GEMPIC.compute_b_from_e!-Tuple{Vector{Float64}, Maxwell1DFEM, Float64, Vector{Float64}}"},"54":{"title":"GEMPIC.compute_e_from_b!","pagetitle":"Maxwell solver","ref":"/gempic/dev/maxwell_solver/#GEMPIC.compute_e_from_b!-Tuple{Vector{Float64}, Maxwell1DFEM, Float64, Vector{Float64}}"},"55":{"title":"GEMPIC.compute_e_from_j!","pagetitle":"Maxwell solver","ref":"/gempic/dev/maxwell_solver/#GEMPIC.compute_e_from_j!-Tuple{Vector{Float64}, Maxwell1DFEM, Vector{Float64}, Int64}"},"56":{"title":"GEMPIC.compute_rhs_from_function!","pagetitle":"Maxwell solver","ref":"/gempic/dev/maxwell_solver/#GEMPIC.compute_rhs_from_function!-Tuple{Vector{Float64}, Maxwell1DFEM, Function, Int64}"},"57":{"title":"GEMPIC.inner_product","pagetitle":"Maxwell solver","ref":"/gempic/dev/maxwell_solver/#GEMPIC.inner_product-NTuple{4, Any}"},"58":{"title":"GEMPIC.l2norm_squared","pagetitle":"Maxwell solver","ref":"/gempic/dev/maxwell_solver/#GEMPIC.l2norm_squared-Tuple{Any, Any, Any}"},"59":{"title":"GEMPIC.l2norm_squared2","pagetitle":"Maxwell solver","ref":"/gempic/dev/maxwell_solver/#GEMPIC.l2norm_squared2-Tuple{Any, Any, Any}"},"60":{"title":"GEMPIC.l2projection!","pagetitle":"Maxwell solver","ref":"/gempic/dev/maxwell_solver/#GEMPIC.l2projection!-Tuple{Vector{Float64}, Maxwell1DFEM, Function, Int64}"},"63":{"title":"Mesh","pagetitle":"Mesh","ref":"/gempic/dev/mesh/#Mesh"},"64":{"title":"GEMPIC.OneDGrid","pagetitle":"Mesh","ref":"/gempic/dev/mesh/#GEMPIC.OneDGrid"},"65":{"title":"GEMPIC.TwoDGrid","pagetitle":"Mesh","ref":"/gempic/dev/mesh/#GEMPIC.TwoDGrid"},"66":{"title":"GEMPIC.get_cell_and_offset","pagetitle":"Mesh","ref":"/gempic/dev/mesh/#GEMPIC.get_cell_and_offset-Tuple{OneDGrid, Any}"},"67":{"title":"GEMPIC.get_x","pagetitle":"Mesh","ref":"/gempic/dev/mesh/#GEMPIC.get_x-Tuple{OneDGrid, Any}"},"70":{"title":"Particle group","pagetitle":"Particle group","ref":"/gempic/dev/particle_group/#Particle-group"},"71":{"title":"GEMPIC.ParticleGroup","pagetitle":"Particle group","ref":"/gempic/dev/particle_group/#GEMPIC.ParticleGroup"},"72":{"title":"GEMPIC.get_charge","pagetitle":"Particle group","ref":"/gempic/dev/particle_group/#GEMPIC.get_charge-Union{Tuple{V}, Tuple{D}, Tuple{ParticleGroup{D, V}, Int64}} where {D, V}"},"73":{"title":"GEMPIC.get_mass","pagetitle":"Particle group","ref":"/gempic/dev/particle_group/#GEMPIC.get_mass-Union{Tuple{V}, Tuple{D}, Tuple{ParticleGroup{D, V}, Int64}} where {D, V}"},"74":{"title":"GEMPIC.get_v","pagetitle":"Particle group","ref":"/gempic/dev/particle_group/#GEMPIC.get_v-Union{Tuple{V}, Tuple{D}, Tuple{ParticleGroup{D, V}, Int64}} where {D, V}"},"75":{"title":"GEMPIC.get_weights","pagetitle":"Particle group","ref":"/gempic/dev/particle_group/#GEMPIC.get_weights-Union{Tuple{V}, Tuple{D}, Tuple{ParticleGroup{D, V}, Int64}} where {D, V}"},"76":{"title":"GEMPIC.get_x","pagetitle":"Particle group","ref":"/gempic/dev/particle_group/#GEMPIC.get_x-Union{Tuple{V}, Tuple{D}, Tuple{ParticleGroup{D, V}, Int64}} where {D, V}"},"77":{"title":"GEMPIC.set_v!","pagetitle":"Particle group","ref":"/gempic/dev/particle_group/#GEMPIC.set_v!-Union{Tuple{V}, Tuple{D}, Tuple{ParticleGroup{D, V}, Int64, Float64}} where {D, V}"},"78":{"title":"GEMPIC.set_v!","pagetitle":"Particle group","ref":"/gempic/dev/particle_group/#GEMPIC.set_v!-Union{Tuple{V}, Tuple{D}, Tuple{ParticleGroup{D, V}, Int64, Vector{Float64}}} where {D, V}"},"79":{"title":"GEMPIC.set_weights!","pagetitle":"Particle group","ref":"/gempic/dev/particle_group/#GEMPIC.set_weights!-Union{Tuple{V}, Tuple{D}, Tuple{ParticleGroup{D, V}, Int64, Float64}} where {D, V}"},"80":{"title":"GEMPIC.set_weights!","pagetitle":"Particle group","ref":"/gempic/dev/particle_group/#GEMPIC.set_weights!-Union{Tuple{V}, Tuple{D}, Tuple{ParticleGroup{D, V}, Int64, Vector{Float64}}} where {D, V}"},"81":{"title":"GEMPIC.set_x!","pagetitle":"Particle group","ref":"/gempic/dev/particle_group/#GEMPIC.set_x!-Union{Tuple{V}, Tuple{D}, Tuple{ParticleGroup{D, V}, Int64, Float64}} where {D, V}"},"82":{"title":"GEMPIC.set_x!","pagetitle":"Particle group","ref":"/gempic/dev/particle_group/#GEMPIC.set_x!-Union{Tuple{V}, Tuple{D}, Tuple{ParticleGroup{D, V}, Int64, Vector{Float64}}} where {D, V}"},"85":{"title":"Particle-Mesh coupling","pagetitle":"Particle-Mesh coupling","ref":"/gempic/dev/particle_mesh_coupling/#Particle-Mesh-coupling"},"86":{"title":"GEMPIC.ParticleMeshCoupling1D","pagetitle":"Particle-Mesh coupling","ref":"/gempic/dev/particle_mesh_coupling/#GEMPIC.ParticleMeshCoupling1D"},"87":{"title":"GEMPIC.add_charge!","pagetitle":"Particle-Mesh coupling","ref":"/gempic/dev/particle_mesh_coupling/#GEMPIC.add_charge!-Tuple{Vector{Float64}, ParticleMeshCoupling1D, Float64, Float64}"},"88":{"title":"GEMPIC.add_charge_pp!","pagetitle":"Particle-Mesh coupling","ref":"/gempic/dev/particle_mesh_coupling/#GEMPIC.add_charge_pp!-Tuple{Vector{Float64}, ParticleMeshCoupling1D, Float64, Any}"},"89":{"title":"GEMPIC.add_current_update_v!","pagetitle":"Particle-Mesh coupling","ref":"/gempic/dev/particle_mesh_coupling/#GEMPIC.add_current_update_v!-Tuple{AbstractArray, ParticleMeshCoupling1D, Float64, Float64, Float64, Float64, Vector{Float64}, Float64}"},"90":{"title":"GEMPIC.add_current_update_v!","pagetitle":"Particle-Mesh coupling","ref":"/gempic/dev/particle_mesh_coupling/#GEMPIC.add_current_update_v!-Tuple{AbstractArray, ParticleMeshCoupling1D, Vararg{Float64, 5}}"},"91":{"title":"GEMPIC.add_current_update_v_pp!","pagetitle":"Particle-Mesh coupling","ref":"/gempic/dev/particle_mesh_coupling/#GEMPIC.add_current_update_v_pp!-Tuple{AbstractArray, ParticleMeshCoupling1D, Any, Any, Float64, Float64, Vector{Float64}, Vector{Float64}}"},"92":{"title":"GEMPIC.evaluate","pagetitle":"Particle-Mesh coupling","ref":"/gempic/dev/particle_mesh_coupling/#GEMPIC.evaluate-Tuple{ParticleMeshCoupling1D, Float64, Vector{Float64}}"},"93":{"title":"GEMPIC.evaluate_pp","pagetitle":"Particle-Mesh coupling","ref":"/gempic/dev/particle_mesh_coupling/#GEMPIC.evaluate_pp-Tuple{ParticleMeshCoupling1D, Float64, Matrix{Float64}}"},"94":{"title":"GEMPIC.update_jv!","pagetitle":"Particle-Mesh coupling","ref":"/gempic/dev/particle_mesh_coupling/#GEMPIC.update_jv!-Tuple{AbstractArray, ParticleMeshCoupling1D, Float64, Float64, Int64, Float64, Float64, Float64, Float64, Vector{Float64}}"},"95":{"title":"GEMPIC.update_jv!","pagetitle":"Particle-Mesh coupling","ref":"/gempic/dev/particle_mesh_coupling/#GEMPIC.update_jv!-Tuple{AbstractArray, ParticleMeshCoupling1D, Float64, Float64, Int64, Vararg{Float64, 4}}"},"96":{"title":"GEMPIC.update_jv_pp!","pagetitle":"Particle-Mesh coupling","ref":"/gempic/dev/particle_mesh_coupling/#GEMPIC.update_jv_pp!-Tuple{AbstractArray, ParticleMeshCoupling1D, Float64, Float64, Int64, Float64, Float64, Float64, Vector{Float64}}"},"97":{"title":"GEMPIC.ParticleMeshCoupling2D","pagetitle":"Particle-Mesh coupling","ref":"/gempic/dev/particle_mesh_coupling/#GEMPIC.ParticleMeshCoupling2D"},"98":{"title":"GEMPIC.add_charge!","pagetitle":"Particle-Mesh coupling","ref":"/gempic/dev/particle_mesh_coupling/#GEMPIC.add_charge!-Tuple{Any, ParticleMeshCoupling2D, Any, Any, Any}"},"99":{"title":"GEMPIC.add_charge_pp!","pagetitle":"Particle-Mesh coupling","ref":"/gempic/dev/particle_mesh_coupling/#GEMPIC.add_charge_pp!-Tuple{Any, ParticleMeshCoupling2D, Any, Any, Any}"},"100":{"title":"GEMPIC.compute_shape_factor","pagetitle":"Particle-Mesh coupling","ref":"/gempic/dev/particle_mesh_coupling/#GEMPIC.compute_shape_factor-Tuple{ParticleMeshCoupling2D, Any, Any}"},"101":{"title":"GEMPIC.evaluate","pagetitle":"Particle-Mesh coupling","ref":"/gempic/dev/particle_mesh_coupling/#GEMPIC.evaluate-NTuple{4, Any}"},"102":{"title":"GEMPIC.evaluate_multiple","pagetitle":"Particle-Mesh coupling","ref":"/gempic/dev/particle_mesh_coupling/#GEMPIC.evaluate_multiple-Tuple{Any, Any, Any}"},"103":{"title":"GEMPIC.evaluate_pp","pagetitle":"Particle-Mesh coupling","ref":"/gempic/dev/particle_mesh_coupling/#GEMPIC.evaluate_pp-Tuple{ParticleMeshCoupling2D, Any, Any, Any}"},"104":{"title":"GEMPIC.index_1dto2d_column_major","pagetitle":"Particle-Mesh coupling","ref":"/gempic/dev/particle_mesh_coupling/#GEMPIC.index_1dto2d_column_major-Tuple{Any, Any, Any}"},"107":{"title":"Particle sampling","pagetitle":"Particle sampling","ref":"/gempic/dev/particle_sampling/#Particle-sampling"},"108":{"title":"GEMPIC.ParticleSampler","pagetitle":"Particle sampling","ref":"/gempic/dev/particle_sampling/#GEMPIC.ParticleSampler"},"109":{"title":"GEMPIC.newton","pagetitle":"Particle sampling","ref":"/gempic/dev/particle_sampling/#GEMPIC.newton-Tuple{Any, Any, Any}"},"110":{"title":"GEMPIC.sample!","pagetitle":"Particle sampling","ref":"/gempic/dev/particle_sampling/#GEMPIC.sample!-Tuple{ParticleGroup{1, 1}, Float64, Float64, Float64, OneDGrid}"},"111":{"title":"GEMPIC.sample!","pagetitle":"Particle sampling","ref":"/gempic/dev/particle_sampling/#GEMPIC.sample!-Tuple{ParticleGroup{1, 2}, Float64, Float64, Float64, OneDGrid}"},"112":{"title":"GEMPIC.sample!","pagetitle":"Particle sampling","ref":"/gempic/dev/particle_sampling/#GEMPIC.sample!-Tuple{ParticleGroup{1, 2}, ParticleSampler, GEMPIC.AbstractCosGaussian, GEMPIC.AbstractGrid}"},"113":{"title":"GEMPIC.sample_all","pagetitle":"Particle sampling","ref":"/gempic/dev/particle_sampling/#GEMPIC.sample_all-Tuple{Any, ParticleGroup{1, 2}, GEMPIC.AbstractCosGaussian, Any}"},"114":{"title":"GEMPIC.sample_sym","pagetitle":"Particle sampling","ref":"/gempic/dev/particle_sampling/#GEMPIC.sample_sym-NTuple{4, Any}"},"115":{"title":"Special case of the Landau Damping","pagetitle":"Particle sampling","ref":"/gempic/dev/particle_sampling/#Special-case-of-the-Landau-Damping"},"116":{"title":"GEMPIC.LandauDamping","pagetitle":"Particle sampling","ref":"/gempic/dev/particle_sampling/#GEMPIC.LandauDamping"},"117":{"title":"GEMPIC.sample!","pagetitle":"Particle sampling","ref":"/gempic/dev/particle_sampling/#GEMPIC.sample!-Tuple{GEMPIC.LandauDamping, ParticleGroup{1, 2}}"},"120":{"title":"Periodic spline","pagetitle":"Periodic spline","ref":"/gempic/dev/splinepp/#Periodic-spline"},"121":{"title":"GEMPIC.SplinePP","pagetitle":"Periodic spline","ref":"/gempic/dev/splinepp/#GEMPIC.SplinePP"},"122":{"title":"GEMPIC.b_to_pp","pagetitle":"Periodic spline","ref":"/gempic/dev/splinepp/#GEMPIC.b_to_pp-Tuple{GEMPIC.SplinePP, Int64, Vector{Float64}}"},"123":{"title":"GEMPIC.b_to_pp_1d_cell!","pagetitle":"Periodic spline","ref":"/gempic/dev/splinepp/#GEMPIC.b_to_pp_1d_cell!-Tuple{Any, Any, Any}"},"124":{"title":"GEMPIC.b_to_pp_2d!","pagetitle":"Periodic spline","ref":"/gempic/dev/splinepp/#GEMPIC.b_to_pp_2d!-Tuple{Any, GEMPIC.SplinePP, GEMPIC.SplinePP, Any}"},"125":{"title":"GEMPIC.b_to_pp_2d_cell!","pagetitle":"Periodic spline","ref":"/gempic/dev/splinepp/#GEMPIC.b_to_pp_2d_cell!-Tuple{Any, GEMPIC.SplinePP, GEMPIC.SplinePP, Any, Any, Any}"},"126":{"title":"GEMPIC.horner_1d","pagetitle":"Periodic spline","ref":"/gempic/dev/splinepp/#GEMPIC.horner_1d-Tuple{Int64, Any, Float64, Int64}"},"127":{"title":"GEMPIC.horner_2d","pagetitle":"Periodic spline","ref":"/gempic/dev/splinepp/#GEMPIC.horner_2d-NTuple{5, Any}"},"128":{"title":"GEMPIC.horner_m_2d!","pagetitle":"Periodic spline","ref":"/gempic/dev/splinepp/#GEMPIC.horner_m_2d!-Tuple{Any, GEMPIC.SplinePP, GEMPIC.SplinePP, Any, Any, Any}"},"129":{"title":"GEMPIC.horner_primitive_1d","pagetitle":"Periodic spline","ref":"/gempic/dev/splinepp/#GEMPIC.horner_primitive_1d-Tuple{Vector{Float64}, Any, Any, Any}"},"132":{"title":"Strong Landau Damping","pagetitle":"Strong Landau Damping","ref":"/gempic/dev/strong_landau_damping/#Strong-Landau-Damping"},"133":{"title":"Initialize field solver","pagetitle":"Strong Landau Damping","ref":"/gempic/dev/strong_landau_damping/#Initialize-field-solver"},"134":{"title":"Simulation function","pagetitle":"Strong Landau Damping","ref":"/gempic/dev/strong_landau_damping/#Simulation-function"},"135":{"title":"Time evolution of electric energy","pagetitle":"Strong Landau Damping","ref":"/gempic/dev/strong_landau_damping/#Time-evolution-of-electric-energy"},"138":{"title":"SemiLagrangian.jl Documentation","pagetitle":"Home","ref":"/semi-lagrangian/dev/#SemiLagrangian.jl-Documentation"},"139":{"title":"SemiLagrangian.SemiLagrangian","pagetitle":"Home","ref":"/semi-lagrangian/dev/#SemiLagrangian.SemiLagrangian"},"142":{"title":"Advection","pagetitle":"Advection","ref":"/semi-lagrangian/dev/advection/#Advection"},"143":{"title":"SemiLagrangian.hamsplit_3_11","pagetitle":"Advection","ref":"/semi-lagrangian/dev/advection/#SemiLagrangian.hamsplit_3_11-Union{Tuple{T}, Tuple{T, Any}} where T<:Number"},"144":{"title":"SemiLagrangian.magicsplit","pagetitle":"Advection","ref":"/semi-lagrangian/dev/advection/#SemiLagrangian.magicsplit-Tuple{T} where T"},"145":{"title":"SemiLagrangian.nosplit","pagetitle":"Advection","ref":"/semi-lagrangian/dev/advection/#SemiLagrangian.nosplit-Tuple{T} where T"},"146":{"title":"SemiLagrangian.order6split","pagetitle":"Advection","ref":"/semi-lagrangian/dev/advection/#SemiLagrangian.order6split-Tuple{T} where T"},"147":{"title":"SemiLagrangian.standardsplit","pagetitle":"Advection","ref":"/semi-lagrangian/dev/advection/#SemiLagrangian.standardsplit-Tuple{T} where T"},"148":{"title":"SemiLagrangian.strangsplit","pagetitle":"Advection","ref":"/semi-lagrangian/dev/advection/#SemiLagrangian.strangsplit-Tuple{T} where T"},"149":{"title":"SemiLagrangian.table2split","pagetitle":"Advection","ref":"/semi-lagrangian/dev/advection/#SemiLagrangian.table2split-Tuple{T} where T"},"150":{"title":"SemiLagrangian.triplejumpsplit","pagetitle":"Advection","ref":"/semi-lagrangian/dev/advection/#SemiLagrangian.triplejumpsplit-Tuple{T} where T"},"151":{"title":"SemiLagrangian.Advection","pagetitle":"Advection","ref":"/semi-lagrangian/dev/advection/#SemiLagrangian.Advection"},"152":{"title":"SemiLagrangian.AdvectionData","pagetitle":"Advection","ref":"/semi-lagrangian/dev/advection/#SemiLagrangian.AdvectionData"},"153":{"title":"SemiLagrangian.StateAdv","pagetitle":"Advection","ref":"/semi-lagrangian/dev/advection/#SemiLagrangian.StateAdv"},"154":{"title":"SemiLagrangian.advection!","pagetitle":"Advection","ref":"/semi-lagrangian/dev/advection/#SemiLagrangian.advection!-Union{Tuple{AdvectionData{T, N, timeopt, timealg}}, Tuple{timealg}, Tuple{timeopt}, Tuple{N}, Tuple{T}} where {T, N, timeopt, timealg}"},"155":{"title":"SemiLagrangian.copydata!","pagetitle":"Advection","ref":"/semi-lagrangian/dev/advection/#SemiLagrangian.copydata!-Union{Tuple{timealg}, Tuple{timeopt}, Tuple{N}, Tuple{T}, Tuple{AdvectionData{T, N, timeopt, timealg}, Any}} where {T, N, timeopt, timealg}"},"156":{"title":"SemiLagrangian.decbegin!","pagetitle":"Advection","ref":"/semi-lagrangian/dev/advection/#SemiLagrangian.decbegin!-Union{Tuple{I}, Tuple{Any, Any, Vector{I}}} where I<:AbstractInterpolation"},"157":{"title":"SemiLagrangian.getformdata","pagetitle":"Advection","ref":"/semi-lagrangian/dev/advection/#SemiLagrangian.getformdata-Tuple{AdvectionData}"},"158":{"title":"SemiLagrangian.initcoef!","pagetitle":"Advection","ref":"/semi-lagrangian/dev/advection/#SemiLagrangian.initcoef!-Union{Tuple{AdvectionData{T, N, timeopt, timealg}}, Tuple{timealg}, Tuple{timeopt}, Tuple{N}, Tuple{T}} where {T, N, timeopt, timealg}"},"159":{"title":"SemiLagrangian.nextstate!","pagetitle":"Advection","ref":"/semi-lagrangian/dev/advection/#SemiLagrangian.nextstate!-Tuple{AdvectionData}"},"160":{"title":"SemiLagrangian.retns","pagetitle":"Advection","ref":"/semi-lagrangian/dev/advection/#SemiLagrangian.retns-Tuple{AdvectionData, SemiLagrangian.AbstractExtDataAdv}"},"161":{"title":"SemiLagrangian.sizeall","pagetitle":"Advection","ref":"/semi-lagrangian/dev/advection/#SemiLagrangian.sizeall-Tuple{Advection}"},"164":{"title":"B-spline","pagetitle":"B-spline","ref":"/semi-lagrangian/dev/bspline/#B-spline"},"165":{"title":"SemiLagrangian.BSpline","pagetitle":"B-spline","ref":"/semi-lagrangian/dev/bspline/#SemiLagrangian.BSpline"},"166":{"title":"SemiLagrangian.BSplineLU","pagetitle":"B-spline","ref":"/semi-lagrangian/dev/bspline/#SemiLagrangian.BSplineLU"},"167":{"title":"SemiLagrangian.LuSpline","pagetitle":"B-spline","ref":"/semi-lagrangian/dev/bspline/#SemiLagrangian.LuSpline"},"168":{"title":"SemiLagrangian.decLULu","pagetitle":"B-spline","ref":"/semi-lagrangian/dev/bspline/#SemiLagrangian.decLULu-NTuple{4, Any}"},"169":{"title":"SemiLagrangian.sol!","pagetitle":"B-spline","ref":"/semi-lagrangian/dev/bspline/#SemiLagrangian.sol!-Union{Tuple{I}, Tuple{T}, Tuple{AbstractVector{I}, BSplineLU{T}, AbstractVector{I}}} where {T, I}"},"170":{"title":"SemiLagrangian.sol!","pagetitle":"B-spline","ref":"/semi-lagrangian/dev/bspline/#SemiLagrangian.sol!-Union{Tuple{I}, Tuple{T}, Tuple{AbstractVector{I}, SemiLagrangian.LuSpline{T}, AbstractVector{I}}} where {T, I}"},"171":{"title":"SemiLagrangian.sol","pagetitle":"B-spline","ref":"/semi-lagrangian/dev/bspline/#SemiLagrangian.sol-Union{Tuple{I}, Tuple{T}, Tuple{BSplineLU{T}, AbstractVector{I}}} where {T<:Number, I}"},"172":{"title":"SemiLagrangian.sol","pagetitle":"B-spline","ref":"/semi-lagrangian/dev/bspline/#SemiLagrangian.sol-Union{Tuple{T}, Tuple{SemiLagrangian.LuSpline{T}, AbstractVector}} where T"},"173":{"title":"SemiLagrangian.BSplineFFT","pagetitle":"B-spline","ref":"/semi-lagrangian/dev/bspline/#SemiLagrangian.BSplineFFT"},"174":{"title":"SemiLagrangian.sol!","pagetitle":"B-spline","ref":"/semi-lagrangian/dev/bspline/#SemiLagrangian.sol!-Union{Tuple{T}, Tuple{AbstractVector{T}, BSplineFFT{T}, AbstractVector{T}}} where T"},"175":{"title":"SemiLagrangian.sol","pagetitle":"B-spline","ref":"/semi-lagrangian/dev/bspline/#SemiLagrangian.sol-Union{Tuple{T}, Tuple{BSplineFFT{T}, AbstractVector{T}}} where T"},"178":{"title":"Index","pagetitle":"Contents","ref":"/semi-lagrangian/dev/contents/#Index"},"181":{"title":"ExtDataAdv","pagetitle":"ExtDataAdv","ref":"/semi-lagrangian/dev/extdataadv/#ExtDataAdv"},"182":{"title":"Functions that needs to be implemented","pagetitle":"ExtDataAdv","ref":"/semi-lagrangian/dev/extdataadv/#Functions-that-needs-to-be-implemented"},"183":{"title":"Methods to define","pagetitle":"ExtDataAdv","ref":"/semi-lagrangian/dev/extdataadv/#Methods-to-define"},"186":{"title":"FFT","pagetitle":"FFT","ref":"/semi-lagrangian/dev/fft/#FFT"},"187":{"title":"SemiLagrangian.PrepareFftBig","pagetitle":"FFT","ref":"/semi-lagrangian/dev/fft/#SemiLagrangian.PrepareFftBig"},"188":{"title":"SemiLagrangian._reverse_num","pagetitle":"FFT","ref":"/semi-lagrangian/dev/fft/#SemiLagrangian._reverse_num-Tuple{Any, Any}"},"189":{"title":"SemiLagrangian.fftbig!","pagetitle":"FFT","ref":"/semi-lagrangian/dev/fft/#SemiLagrangian.fftbig!-Union{Tuple{DIMS}, Tuple{NUMDIMS}, Tuple{T}, Tuple{SemiLagrangian.PrepareFftBig{T, NUMDIMS, DIMS}, Any}} where {T, NUMDIMS, DIMS}"},"192":{"title":"Hermite","pagetitle":"Hermite","ref":"/semi-lagrangian/dev/hermite/#Hermite"},"193":{"title":"SemiLagrangian.Hermite","pagetitle":"Hermite","ref":"/semi-lagrangian/dev/hermite/#SemiLagrangian.Hermite"},"194":{"title":"SemiLagrangian.PrecalHermite","pagetitle":"Hermite","ref":"/semi-lagrangian/dev/hermite/#SemiLagrangian.PrecalHermite"},"197":{"title":"Interpolations","pagetitle":"Interpolations","ref":"/semi-lagrangian/dev/interpolations/#Interpolations"},"198":{"title":"SemiLagrangian.AbstractInterpolation","pagetitle":"Interpolations","ref":"/semi-lagrangian/dev/interpolations/#SemiLagrangian.AbstractInterpolation"},"199":{"title":"SemiLagrangian.CachePrecal","pagetitle":"Interpolations","ref":"/semi-lagrangian/dev/interpolations/#SemiLagrangian.CachePrecal"},"200":{"title":"SemiLagrangian.ValInv","pagetitle":"Interpolations","ref":"/semi-lagrangian/dev/interpolations/#SemiLagrangian.ValInv"},"201":{"title":"Base.isless","pagetitle":"Interpolations","ref":"/semi-lagrangian/dev/interpolations/#Base.isless-Union{Tuple{T}, Tuple{SemiLagrangian.ValInv{T}, SemiLagrangian.ValInv{T}}} where T"},"202":{"title":"SemiLagrangian.autointerp!","pagetitle":"Interpolations","ref":"/semi-lagrangian/dev/interpolations/#SemiLagrangian.autointerp!-Union{Tuple{I}, Tuple{T}, Tuple{N}, Tuple{Array{OpTuple{N, T}, N}, Array{OpTuple{N, T}, N}, Int64, AbstractVector{I}}} where {N, T, I<:AbstractInterpolation}"},"203":{"title":"SemiLagrangian.get_allprecal","pagetitle":"Interpolations","ref":"/semi-lagrangian/dev/interpolations/#SemiLagrangian.get_allprecal-Union{Tuple{order}, Tuple{T}, Tuple{AbstractInterpolation{T, SemiLagrangian.InsideEdge, order}, Int64, T}} where {T, order}"},"204":{"title":"SemiLagrangian.get_order","pagetitle":"Interpolations","ref":"/semi-lagrangian/dev/interpolations/#SemiLagrangian.get_order-Union{Tuple{AbstractInterpolation{T, edge, order}}, Tuple{order}, Tuple{edge}, Tuple{T}} where {T, edge, order}"},"205":{"title":"SemiLagrangian.getinverse","pagetitle":"Interpolations","ref":"/semi-lagrangian/dev/interpolations/#SemiLagrangian.getinverse-Union{Tuple{I}, Tuple{N}, Tuple{T}, Tuple{Tuple{Vararg{Array{T, N}, N}}, Vector{I}}} where {T, N, I<:(AbstractInterpolation{T, SemiLagrangian.CircEdge})}"},"206":{"title":"SemiLagrangian.getprecal","pagetitle":"Interpolations","ref":"/semi-lagrangian/dev/interpolations/#SemiLagrangian.getprecal-Union{Tuple{N}, Tuple{T}, Tuple{SemiLagrangian.CachePrecal{T, N}, Tuple{Vararg{T, N}}}} where {T, N}"},"207":{"title":"SemiLagrangian.getprecal","pagetitle":"Interpolations","ref":"/semi-lagrangian/dev/interpolations/#SemiLagrangian.getprecal-Union{Tuple{T}, Tuple{N}, Tuple{SemiLagrangian.CachePrecal{T, N}, OpTuple{N, T}}} where {N, T<:Real}"},"208":{"title":"SemiLagrangian.getprecal","pagetitle":"Interpolations","ref":"/semi-lagrangian/dev/interpolations/#SemiLagrangian.getprecal-Union{Tuple{T}, Tuple{SemiLagrangian.CachePrecal{T, 1}, Tuple{T}}} where T"},"209":{"title":"SemiLagrangian.getprecal","pagetitle":"Interpolations","ref":"/semi-lagrangian/dev/interpolations/#SemiLagrangian.getprecal-Union{Tuple{T}, Tuple{SemiLagrangian.CachePrecal{T, 1}, T}} where T"},"210":{"title":"SemiLagrangian.getprecal","pagetitle":"Interpolations","ref":"/semi-lagrangian/dev/interpolations/#SemiLagrangian.getprecal-Union{Tuple{T}, Tuple{SemiLagrangian.CachePrecal{T, 2}, Complex{T}}} where T<:Real"},"211":{"title":"SemiLagrangian.interpbufc!","pagetitle":"Interpolations","ref":"/semi-lagrangian/dev/interpolations/#SemiLagrangian.interpbufc!-Union{Tuple{I}, Tuple{T}, Tuple{N}, Tuple{Array{Array{OpTuple{N, T}, N}, 1}, Array{OpTuple{N, T}, N}, AbstractVector{I}}, Tuple{Array{Array{OpTuple{N, T}, N}, 1}, Array{OpTuple{N, T}, N}, AbstractVector{I}, Int64}} where {N, T, I<:(AbstractInterpolation{T})}"},"212":{"title":"SemiLagrangian.interpolate!","pagetitle":"Interpolations","ref":"/semi-lagrangian/dev/interpolations/#SemiLagrangian.interpolate!-Union{Tuple{I}, Tuple{N}, Tuple{T}, Tuple{AbstractArray{T, N}, AbstractArray{T, N}, Tuple{Vararg{Int64, N}}, Array{T, N}, Vector{I}}, Tuple{AbstractArray{T, N}, AbstractArray{T, N}, Tuple{Vararg{Int64, N}}, Array{T, N}, Vector{I}, Any}} where {T, N, I<:(AbstractInterpolation{T, SemiLagrangian.CircEdge})}"},"213":{"title":"SemiLagrangian.interpolate!","pagetitle":"Interpolations","ref":"/semi-lagrangian/dev/interpolations/#SemiLagrangian.interpolate!-Union{Tuple{I}, Tuple{N}, Tuple{T}, Tuple{Union{AbstractArray{T, N}, AbstractArray{Complex{T}, N}, AbstractArray{OpTuple{N, T}, N}}, Union{AbstractArray{T, N}, AbstractArray{Complex{T}, N}, AbstractArray{OpTuple{N, T}, N}}, Union{AbstractArray{Complex{T}, N}, AbstractArray{OpTuple{N, T}, N}}, AbstractVector{I}}} where {T, N, I<:(AbstractInterpolation{T})}"},"214":{"title":"SemiLagrangian.interpolate!","pagetitle":"Interpolations","ref":"/semi-lagrangian/dev/interpolations/#SemiLagrangian.interpolate!-Union{Tuple{I}, Tuple{N}, Tuple{T}, Tuple{Union{AbstractArray{T, N}, AbstractArray{Complex{T}, N}}, Union{AbstractArray{T, N}, AbstractArray{Complex{T}, N}}, Function, AbstractVector{I}}} where {T, N, I<:(AbstractInterpolation{T})}"},"215":{"title":"SemiLagrangian.interpolate!","pagetitle":"Interpolations","ref":"/semi-lagrangian/dev/interpolations/#SemiLagrangian.interpolate!-Union{Tuple{I}, Tuple{T}, Tuple{AbstractVector{T}, AbstractVector{T}, Int64, Vector{T}, Vector{I}}, Tuple{AbstractVector{T}, AbstractVector{T}, Int64, Vector{T}, Vector{I}, Any}} where {T, I<:(AbstractInterpolation{T, SemiLagrangian.CircEdge})}"},"216":{"title":"SemiLagrangian.interpolate!","pagetitle":"Interpolations","ref":"/semi-lagrangian/dev/interpolations/#SemiLagrangian.interpolate!-Union{Tuple{order}, Tuple{T}, Tuple{AbstractVector{T}, AbstractVector{T}, Int64, Array{Vector{T}, 1}, AbstractInterpolation{T, SemiLagrangian.InsideEdge, order}}, Tuple{AbstractVector{T}, AbstractVector{T}, Int64, Array{Vector{T}, 1}, AbstractInterpolation{T, SemiLagrangian.InsideEdge, order}, Any}} where {T, order}"},"217":{"title":"SemiLagrangian.interpolate!","pagetitle":"Interpolations","ref":"/semi-lagrangian/dev/interpolations/#SemiLagrangian.interpolate!-Union{Tuple{order}, Tuple{T}, Tuple{AbstractVector{T}, AbstractVector{T}, Int64, Vector{T}, AbstractInterpolation{T, SemiLagrangian.CircEdge, order}}, Tuple{AbstractVector{T}, AbstractVector{T}, Int64, Vector{T}, AbstractInterpolation{T, SemiLagrangian.CircEdge, order}, Any}} where {T, order}"},"218":{"title":"SemiLagrangian.interpolate!","pagetitle":"Interpolations","ref":"/semi-lagrangian/dev/interpolations/#SemiLagrangian.interpolate!-Union{Tuple{order}, Tuple{edge}, Tuple{T}, Tuple{Any, Any, Any, AbstractInterpolation{T, edge, order}}} where {T, edge, order}"},"219":{"title":"SemiLagrangian.interpolatemod!","pagetitle":"Interpolations","ref":"/semi-lagrangian/dev/interpolations/#SemiLagrangian.interpolatemod!-Union{Tuple{I}, Tuple{N}, Tuple{T}, Tuple{AbstractArray{T, N}, AbstractArray{T, N}, Tuple{Array{T, N}, Array{T, N}}, AbstractVector{I}, Union{UniformMesh{T}, T}}} where {T, N, I<:(AbstractInterpolation{T, SemiLagrangian.CircEdge})}"},"220":{"title":"SemiLagrangian.sol","pagetitle":"Interpolations","ref":"/semi-lagrangian/dev/interpolations/#SemiLagrangian.sol-Tuple{AbstractInterpolation, AbstractArray}"},"221":{"title":"SemiLagrangian.sol","pagetitle":"Interpolations","ref":"/semi-lagrangian/dev/interpolations/#SemiLagrangian.sol-Union{Tuple{I}, Tuple{N}, Tuple{T}, Tuple{AbstractVector{I}, Union{AbstractArray{T, N}, AbstractArray{Complex{T}, N}, AbstractArray{OpTuple{N, T}, N}}}} where {T<:Real, N, I<:(AbstractInterpolation{T})}"},"224":{"title":"Lagrange interpolation","pagetitle":"Lagrange interpolation","ref":"/semi-lagrangian/dev/lagrange/#Lagrange-interpolation"},"225":{"title":"SemiLagrangian.Lagrange","pagetitle":"Lagrange interpolation","ref":"/semi-lagrangian/dev/lagrange/#SemiLagrangian.Lagrange"},"226":{"title":"SemiLagrangian._getpolylagrange","pagetitle":"Lagrange interpolation","ref":"/semi-lagrangian/dev/lagrange/#SemiLagrangian._getpolylagrange-Tuple{Int64, Int64, Int64}"},"229":{"title":"Meshes","pagetitle":"Meshes","ref":"/semi-lagrangian/dev/meshes/#Meshes"},"230":{"title":"SemiLagrangian.UniformMesh","pagetitle":"Meshes","ref":"/semi-lagrangian/dev/meshes/#SemiLagrangian.UniformMesh"},"231":{"title":"Base.length","pagetitle":"Meshes","ref":"/semi-lagrangian/dev/meshes/#Base.length-Tuple{UniformMesh}"},"232":{"title":"Base.step","pagetitle":"Meshes","ref":"/semi-lagrangian/dev/meshes/#Base.step-Tuple{UniformMesh}"},"233":{"title":"SemiLagrangian.meshtostd","pagetitle":"Meshes","ref":"/semi-lagrangian/dev/meshes/#SemiLagrangian.meshtostd-Union{Tuple{T}, Tuple{UniformMesh{T}, Any}} where T"},"234":{"title":"SemiLagrangian.points","pagetitle":"Meshes","ref":"/semi-lagrangian/dev/meshes/#SemiLagrangian.points-Tuple{UniformMesh}"},"235":{"title":"SemiLagrangian.start","pagetitle":"Meshes","ref":"/semi-lagrangian/dev/meshes/#SemiLagrangian.start-Tuple{UniformMesh}"},"236":{"title":"SemiLagrangian.stdtomesh","pagetitle":"Meshes","ref":"/semi-lagrangian/dev/meshes/#SemiLagrangian.stdtomesh-Union{Tuple{T}, Tuple{UniformMesh{T}, Any}} where T"},"237":{"title":"SemiLagrangian.stop","pagetitle":"Meshes","ref":"/semi-lagrangian/dev/meshes/#SemiLagrangian.stop-Tuple{UniformMesh}"},"238":{"title":"SemiLagrangian.traitmodbegin!","pagetitle":"Meshes","ref":"/semi-lagrangian/dev/meshes/#SemiLagrangian.traitmodbegin!-Union{Tuple{N}, Tuple{T}, Tuple{UniformMesh{T}, Array{T, N}}} where {T, N}"},"239":{"title":"SemiLagrangian.traitmodbegin!","pagetitle":"Meshes","ref":"/semi-lagrangian/dev/meshes/#SemiLagrangian.traitmodbegin!-Union{Tuple{T2}, Tuple{N}, Tuple{T2, Array{T2, N}}} where {N, T2<:Union{Number, OpTuple{N, <:Number}}}"},"240":{"title":"SemiLagrangian.traitmodend!","pagetitle":"Meshes","ref":"/semi-lagrangian/dev/meshes/#SemiLagrangian.traitmodend!-Union{Tuple{N}, Tuple{T}, Tuple{UniformMesh{T}, Array{T, N}}} where {T, N}"},"241":{"title":"SemiLagrangian.traitmodend!","pagetitle":"Meshes","ref":"/semi-lagrangian/dev/meshes/#SemiLagrangian.traitmodend!-Union{Tuple{T2}, Tuple{N}, Tuple{T2, Array{T2, N}}} where {N, T2<:Union{Number, OpTuple{N, <:Number}}}"},"242":{"title":"SemiLagrangian.vec_k_fft","pagetitle":"Meshes","ref":"/semi-lagrangian/dev/meshes/#SemiLagrangian.vec_k_fft-Union{Tuple{UniformMesh{T}}, Tuple{T}} where T"},"243":{"title":"SemiLagrangian.width","pagetitle":"Meshes","ref":"/semi-lagrangian/dev/meshes/#SemiLagrangian.width-Tuple{UniformMesh}"},"246":{"title":"Two-dimensional problems","pagetitle":"Two dimensions","ref":"/semi-lagrangian/dev/modele_2d/#Two-dimensional-problems"},"247":{"title":"General context","pagetitle":"Two dimensions","ref":"/semi-lagrangian/dev/modele_2d/#General-context"},"248":{"title":"Details on the  $2D$  semi-Lagrangian method","pagetitle":"Two dimensions","ref":"/semi-lagrangian/dev/modele_2d/#Details-on-the-2D-semi-Lagrangian-method"},"249":{"title":"ODE solver","pagetitle":"Two dimensions","ref":"/semi-lagrangian/dev/modele_2d/#ODE-solver"},"250":{"title":"First order","pagetitle":"Two dimensions","ref":"/semi-lagrangian/dev/modele_2d/#First-order"},"251":{"title":"Second order","pagetitle":"Two dimensions","ref":"/semi-lagrangian/dev/modele_2d/#Second-order"},"252":{"title":"Extension to higher order","pagetitle":"Two dimensions","ref":"/semi-lagrangian/dev/modele_2d/#Extension-to-higher-order"},"253":{"title":"$2D$  Interpolation","pagetitle":"Two dimensions","ref":"/semi-lagrangian/dev/modele_2d/#2D-Interpolation"},"254":{"title":"Lagrange interpolation","pagetitle":"Two dimensions","ref":"/semi-lagrangian/dev/modele_2d/#Lagrange-interpolation"},"255":{"title":"Splines interpolation","pagetitle":"Two dimensions","ref":"/semi-lagrangian/dev/modele_2d/#Splines-interpolation"},"256":{"title":"Some examples","pagetitle":"Two dimensions","ref":"/semi-lagrangian/dev/modele_2d/#Some-examples"},"257":{"title":"Example 1 : rotation","pagetitle":"Two dimensions","ref":"/semi-lagrangian/dev/modele_2d/#Example-1-:-rotation"},"258":{"title":"Example 2 : swirling deformation flow","pagetitle":"Two dimensions","ref":"/semi-lagrangian/dev/modele_2d/#Example-2-:-swirling-deformation-flow"},"259":{"title":"Example 3: Vlasov-Poisson","pagetitle":"Two dimensions","ref":"/semi-lagrangian/dev/modele_2d/#Example-3:-Vlasov-Poisson"},"260":{"title":"Example 4: Guiding-center","pagetitle":"Two dimensions","ref":"/semi-lagrangian/dev/modele_2d/#Example-4:-Guiding-center"},"261":{"title":"References","pagetitle":"Two dimensions","ref":"/semi-lagrangian/dev/modele_2d/#References"},"264":{"title":"Poisson solver","pagetitle":"Poisson solver","ref":"/semi-lagrangian/dev/poisson/#Poisson-solver"},"265":{"title":"SemiLagrangian.PoissonConst","pagetitle":"Poisson solver","ref":"/semi-lagrangian/dev/poisson/#SemiLagrangian.PoissonConst"},"266":{"title":"SemiLagrangian.PoissonVar","pagetitle":"Poisson solver","ref":"/semi-lagrangian/dev/poisson/#SemiLagrangian.PoissonVar"},"267":{"title":"SemiLagrangian._get_fctv_k","pagetitle":"Poisson solver","ref":"/semi-lagrangian/dev/poisson/#SemiLagrangian._get_fctv_k-Union{Tuple{Advection{T, N, timeopt}}, Tuple{timeopt}, Tuple{N}, Tuple{T}} where {T, N, timeopt}"},"268":{"title":"SemiLagrangian.compute_charge!","pagetitle":"Poisson solver","ref":"/semi-lagrangian/dev/poisson/#SemiLagrangian.compute_charge!-Union{Tuple{Nsum}, Tuple{Nv}, Tuple{Nsp}, Tuple{T}, Tuple{Array{T, Nsp}, Tuple{Vararg{UniformMesh{T}, Nv}}, Array{T, Nsum}}} where {T, Nsp, Nv, Nsum}"},"269":{"title":"SemiLagrangian.compute_charge!","pagetitle":"Poisson solver","ref":"/semi-lagrangian/dev/poisson/#SemiLagrangian.compute_charge!-Union{Tuple{Nv}, Tuple{Nsp}, Tuple{N}, Tuple{T}, Tuple{SemiLagrangian.PoissonVar{T, N, Nsp, Nv}, AdvectionData}} where {T, N, Nsp, Nv}"},"270":{"title":"SemiLagrangian.compute_ee","pagetitle":"Poisson solver","ref":"/semi-lagrangian/dev/poisson/#SemiLagrangian.compute_ee-Tuple{AdvectionData}"},"271":{"title":"SemiLagrangian.compute_ee","pagetitle":"Poisson solver","ref":"/semi-lagrangian/dev/poisson/#SemiLagrangian.compute_ee-Union{Tuple{N}, Tuple{T}, Tuple{Tuple{Vararg{UniformMesh{T}, N}}, Tuple{Vararg{Array{T, N}, N}}}} where {T, N}"},"272":{"title":"SemiLagrangian.compute_elfield!","pagetitle":"Poisson solver","ref":"/semi-lagrangian/dev/poisson/#SemiLagrangian.compute_elfield!-Union{Tuple{SemiLagrangian.PoissonVar{T, N, Nsp, Nv}}, Tuple{Nv}, Tuple{Nsp}, Tuple{N}, Tuple{T}} where {T, N, Nsp, Nv}"},"273":{"title":"SemiLagrangian.compute_elfield!","pagetitle":"Poisson solver","ref":"/semi-lagrangian/dev/poisson/#SemiLagrangian.compute_elfield!-Union{Tuple{T}, Tuple{Vector{T}, UniformMesh{T}, Vector{T}}} where T"},"274":{"title":"SemiLagrangian.compute_elfield","pagetitle":"Poisson solver","ref":"/semi-lagrangian/dev/poisson/#SemiLagrangian.compute_elfield-Union{Tuple{N}, Tuple{T}, Tuple{Tuple{Vararg{UniformMesh{T}, N}}, Array{T, N}, Any}} where {T<:AbstractFloat, N}"},"275":{"title":"SemiLagrangian.compute_ke","pagetitle":"Poisson solver","ref":"/semi-lagrangian/dev/poisson/#SemiLagrangian.compute_ke-Union{Tuple{AdvectionData{T, N}}, Tuple{N}, Tuple{T}} where {T, N}"},"276":{"title":"SemiLagrangian.compute_ke","pagetitle":"Poisson solver","ref":"/semi-lagrangian/dev/poisson/#SemiLagrangian.compute_ke-Union{Tuple{Nsum}, Tuple{Nv}, Tuple{Nsp}, Tuple{T}, Tuple{Tuple{Vararg{UniformMesh{T}, Nsp}}, Tuple{Vararg{UniformMesh{T}, Nv}}, Array{T, Nsum}}} where {T, Nsp, Nv, Nsum}"},"277":{"title":"SemiLagrangian.getalpha","pagetitle":"Poisson solver","ref":"/semi-lagrangian/dev/poisson/#SemiLagrangian.getalpha-Union{Tuple{Nv}, Tuple{Nsp}, Tuple{N}, Tuple{T}, Tuple{SemiLagrangian.PoissonVar{T, N, Nsp, Nv, StdPoisson}, AdvectionData{T}, Any}} where {T, N, Nsp, Nv}"},"278":{"title":"SemiLagrangian.getenergy","pagetitle":"Poisson solver","ref":"/semi-lagrangian/dev/poisson/#SemiLagrangian.getenergy-Tuple{AdvectionData}"},"279":{"title":"SemiLagrangian.getenergyall","pagetitle":"Poisson solver","ref":"/semi-lagrangian/dev/poisson/#SemiLagrangian.getenergyall-Tuple{AdvectionData}"},"280":{"title":"SemiLagrangian.getpoissonvar","pagetitle":"Poisson solver","ref":"/semi-lagrangian/dev/poisson/#SemiLagrangian.getpoissonvar-Tuple{Advection}"},"281":{"title":"SemiLagrangian.initcoef!","pagetitle":"Poisson solver","ref":"/semi-lagrangian/dev/poisson/#SemiLagrangian.initcoef!-Union{Tuple{Nv}, Tuple{Nsp}, Tuple{N}, Tuple{T}, Tuple{SemiLagrangian.PoissonVar{T, N, Nsp, Nv, StdPoisson}, AdvectionData{T, N}}} where {T, N, Nsp, Nv}"},"282":{"title":"SemiLagrangian.initcoef!","pagetitle":"Poisson solver","ref":"/semi-lagrangian/dev/poisson/#SemiLagrangian.initcoef!-Union{Tuple{timeopt}, Tuple{Nv}, Tuple{Nsp}, Tuple{N}, Tuple{T}, Tuple{SemiLagrangian.PoissonVar{T, N, Nsp, Nv, StdPoisson2d}, AdvectionData{T, N, timeopt}}} where {T, N, Nsp, Nv, timeopt}"},"283":{"title":"SemiLagrangian.isvelocity","pagetitle":"Poisson solver","ref":"/semi-lagrangian/dev/poisson/#SemiLagrangian.isvelocity-Union{Tuple{Nv}, Tuple{Nsp}, Tuple{N}, Tuple{T}, Tuple{SemiLagrangian.PoissonVar{T, N, Nsp, Nv}, AdvectionData{T, N}}} where {T, N, Nsp, Nv}"},"286":{"title":"Rotation","pagetitle":"Rotation","ref":"/semi-lagrangian/dev/rotation/#Rotation"},"287":{"title":"SemiLagrangian.RotationVar","pagetitle":"Rotation","ref":"/semi-lagrangian/dev/rotation/#SemiLagrangian.RotationVar"},"288":{"title":"SemiLagrangian.getalpha","pagetitle":"Rotation","ref":"/semi-lagrangian/dev/rotation/#SemiLagrangian.getalpha-Tuple{SemiLagrangian.RotationVar, AdvectionData, Any}"},"289":{"title":"SemiLagrangian.getrotationvar","pagetitle":"Rotation","ref":"/semi-lagrangian/dev/rotation/#SemiLagrangian.getrotationvar-Tuple{Advection}"},"290":{"title":"SemiLagrangian.initcoef!","pagetitle":"Rotation","ref":"/semi-lagrangian/dev/rotation/#SemiLagrangian.initcoef!-Union{Tuple{timeopt}, Tuple{N}, Tuple{T}, Tuple{SemiLagrangian.RotationVar{T, N}, AdvectionData{T, N, timeopt, NoTimeAlg}}} where {T, N, timeopt}"},"291":{"title":"SemiLagrangian.initcoef!","pagetitle":"Rotation","ref":"/semi-lagrangian/dev/rotation/#SemiLagrangian.initcoef!-Union{Tuple{timeopt}, Tuple{T}, Tuple{SemiLagrangian.RotationVar{T, 2}, Union{AdvectionData{T, 2, timeopt, ABTimeAlg_ip}, AdvectionData{T, 2, timeopt, ABTimeAlg_new}}}} where {T, timeopt}"},"296":{"title":"Surface Quasi-Geostrosphic","pagetitle":"Surface Quasi-Geostrosphic","ref":"/semi-lagrangian/dev/surfacequasigeostrophic/#Surface-Quasi-Geostrosphic"},"297":{"title":"SemiLagrangian.GeoConst","pagetitle":"Surface Quasi-Geostrosphic","ref":"/semi-lagrangian/dev/surfacequasigeostrophic/#SemiLagrangian.GeoConst"},"298":{"title":"SemiLagrangian.GeoVar","pagetitle":"Surface Quasi-Geostrosphic","ref":"/semi-lagrangian/dev/surfacequasigeostrophic/#SemiLagrangian.GeoVar"},"299":{"title":"SemiLagrangian.getalpha","pagetitle":"Surface Quasi-Geostrosphic","ref":"/semi-lagrangian/dev/surfacequasigeostrophic/#SemiLagrangian.getalpha-Union{Tuple{N}, Tuple{T}, Tuple{SemiLagrangian.GeoVar{T, N}, AdvectionData{T}, CartesianIndex, CartesianIndex}} where {T, N}"},"300":{"title":"SemiLagrangian.getgeovar","pagetitle":"Surface Quasi-Geostrosphic","ref":"/semi-lagrangian/dev/surfacequasigeostrophic/#SemiLagrangian.getgeovar-Union{Tuple{Advection{T, N}}, Tuple{N}, Tuple{T}} where {T, N}"},"301":{"title":"SemiLagrangian.initcoef!","pagetitle":"Surface Quasi-Geostrosphic","ref":"/semi-lagrangian/dev/surfacequasigeostrophic/#SemiLagrangian.initcoef!-Union{Tuple{N}, Tuple{T}, Tuple{SemiLagrangian.GeoVar{T, N}, AdvectionData{T, N}}} where {T, N}"},"302":{"title":"SemiLagrangian.initdata!","pagetitle":"Surface Quasi-Geostrosphic","ref":"/semi-lagrangian/dev/surfacequasigeostrophic/#SemiLagrangian.initdata!-Union{Tuple{N}, Tuple{T}, Tuple{SemiLagrangian.GeoVar{T, N}, AdvectionData{T, N}}} where {T, N}"},"305":{"title":"Translation","pagetitle":"Translation","ref":"/semi-lagrangian/dev/translation/#Translation"},"306":{"title":"SemiLagrangian.TranslationVar","pagetitle":"Translation","ref":"/semi-lagrangian/dev/translation/#SemiLagrangian.TranslationVar"},"307":{"title":"SemiLagrangian.getalpha","pagetitle":"Translation","ref":"/semi-lagrangian/dev/translation/#SemiLagrangian.getalpha-Union{Tuple{N}, Tuple{T}, Tuple{SemiLagrangian.TranslationVar{T, N}, AdvectionData{T, N}, Any}} where {T, N}"},"308":{"title":"SemiLagrangian.gettranslationvar","pagetitle":"Translation","ref":"/semi-lagrangian/dev/translation/#SemiLagrangian.gettranslationvar-Union{Tuple{Tuple{Vararg{T, N}}}, Tuple{N}, Tuple{T}} where {T, N}"},"309":{"title":"SemiLagrangian.initcoef!","pagetitle":"Translation","ref":"/semi-lagrangian/dev/translation/#SemiLagrangian.initcoef!-Union{Tuple{N}, Tuple{T}, Tuple{SemiLagrangian.TranslationVar{T, N}, AdvectionData{T, N}}} where {T, N}"},"312":{"title":"Vlasov-Poisson","pagetitle":"Vlasov-Poisson","ref":"/semi-lagrangian/dev/vlasov-poisson/#Vlasov-Poisson"},"315":{"title":"VlasovSolvers.jl","pagetitle":"Home","ref":"/vlasov-solvers/dev/#VlasovSolvers.jl"},"316":{"title":"Splitting","pagetitle":"Home","ref":"/vlasov-solvers/dev/#Splitting"},"317":{"title":"Semi-Lagrangian method","pagetitle":"Home","ref":"/vlasov-solvers/dev/#Semi-Lagrangian-method"},"318":{"title":"Poisson equation","pagetitle":"Home","ref":"/vlasov-solvers/dev/#Poisson-equation"},"319":{"title":"Algorithm","pagetitle":"Home","ref":"/vlasov-solvers/dev/#Algorithm"},"322":{"title":"Types and functions","pagetitle":"API","ref":"/vlasov-solvers/dev/api/#Types-and-functions"},"323":{"title":"VlasovSolvers.VlasovSolution1D1V","pagetitle":"API","ref":"/vlasov-solvers/dev/api/#VlasovSolvers.VlasovSolution1D1V"},"324":{"title":"VlasovSolvers.advection!","pagetitle":"API","ref":"/vlasov-solvers/dev/api/#VlasovSolvers.advection!"},"325":{"title":"VlasovSolvers.advection_x!","pagetitle":"API","ref":"/vlasov-solvers/dev/api/#VlasovSolvers.advection_x!"},"326":{"title":"VlasovSolvers.advection_v!","pagetitle":"API","ref":"/vlasov-solvers/dev/api/#VlasovSolvers.advection_v!"},"327":{"title":"VlasovSolvers.solve","pagetitle":"API","ref":"/vlasov-solvers/dev/api/#VlasovSolvers.solve"},"328":{"title":"VlasovSolvers.compute_e","pagetitle":"API","ref":"/vlasov-solvers/dev/api/#VlasovSolvers.compute_e"},"329":{"title":"VlasovSolvers.compute_rho","pagetitle":"API","ref":"/vlasov-solvers/dev/api/#VlasovSolvers.compute_rho"},"330":{"title":"VlasovSolvers.two_stream_instability!","pagetitle":"API","ref":"/vlasov-solvers/dev/api/#VlasovSolvers.two_stream_instability!"},"331":{"title":"VlasovSolvers.Fourier","pagetitle":"API","ref":"/vlasov-solvers/dev/api/#VlasovSolvers.Fourier"},"332":{"title":"VlasovSolvers.BSLLagrange","pagetitle":"API","ref":"/vlasov-solvers/dev/api/#VlasovSolvers.BSLLagrange"},"333":{"title":"VlasovSolvers.bspline","pagetitle":"API","ref":"/vlasov-solvers/dev/api/#VlasovSolvers.bspline"},"336":{"title":"Bump On Tail","pagetitle":"Bump On Tail","ref":"/vlasov-solvers/dev/bump_on_tail/#Bump-On-Tail"},"339":{"title":"Contents","pagetitle":"Contents","ref":"/vlasov-solvers/dev/contents/#Contents"},"340":{"title":"Index","pagetitle":"Contents","ref":"/vlasov-solvers/dev/contents/#Index"},"343":{"title":"Quickstart - Landan damping simulation","pagetitle":"Quickstart","ref":"/vlasov-solvers/dev/problem/#Quickstart-Landan-damping-simulation"},"344":{"title":"Vlasov-Poisson","pagetitle":"Quickstart","ref":"/vlasov-solvers/dev/problem/#Vlasov-Poisson"},"345":{"title":"Landau damping","pagetitle":"Quickstart","ref":"/vlasov-solvers/dev/problem/#Landau-damping"},"346":{"title":"VlasovSolvers.OneDGrid","pagetitle":"Quickstart","ref":"/vlasov-solvers/dev/problem/#VlasovSolvers.OneDGrid"},"347":{"title":"VlasovSolvers.DistributionFunction","pagetitle":"Quickstart","ref":"/vlasov-solvers/dev/problem/#VlasovSolvers.DistributionFunction"},"348":{"title":"VlasovSolvers.landau!","pagetitle":"Quickstart","ref":"/vlasov-solvers/dev/problem/#VlasovSolvers.landau!"},"349":{"title":"VlasovSolvers.VlasovProblem","pagetitle":"Quickstart","ref":"/vlasov-solvers/dev/problem/#VlasovSolvers.VlasovProblem"},"350":{"title":"VlasovSolvers.BSLSpline","pagetitle":"Quickstart","ref":"/vlasov-solvers/dev/problem/#VlasovSolvers.BSLSpline"},"351":{"title":"Simulation with Lagrange interpolation","pagetitle":"Quickstart","ref":"/vlasov-solvers/dev/problem/#Simulation-with-Lagrange-interpolation"},"354":{"title":"Rotation of a gaussian distribution","pagetitle":"Rotation 2D","ref":"/vlasov-solvers/dev/rotation2d/#Rotation-of-a-gaussian-distribution"},"357":{"title":"Swirling flow","pagetitle":"Swirling flow","ref":"/vlasov-solvers/dev/swirling-flow/#Swirling-flow"},"360":{"title":"Two-stream instability","pagetitle":"Two-stream instability","ref":"/vlasov-solvers/dev/tsi/#Two-stream-instability"},"363":{"title":"Vlasov–Ampere","pagetitle":"Vlasov-Ampere","ref":"/vlasov-solvers/dev/vlasov-ampere/#Vlasov–Ampere"},"364":{"title":"Algorithm","pagetitle":"Vlasov-Ampere","ref":"/vlasov-solvers/dev/vlasov-ampere/#Algorithm"},"367":{"title":"Vlasov HMF","pagetitle":"Vlasov-HMF","ref":"/vlasov-solvers/dev/vlasov-hmf/#Vlasov-HMF"},"368":{"title":"Benchmarks","pagetitle":"Vlasov-HMF","ref":"/vlasov-solvers/dev/vlasov-hmf/#Benchmarks"},"369":{"title":"Landau damping","pagetitle":"Vlasov-HMF","ref":"/vlasov-solvers/dev/vlasov-hmf/#Landau-damping"},"370":{"title":"$k_x = 0.5$","pagetitle":"Vlasov-HMF","ref":"/vlasov-solvers/dev/vlasov-hmf/#k_x-0.5"},"371":{"title":"$k_x = 0.4$","pagetitle":"Vlasov-HMF","ref":"/vlasov-solvers/dev/vlasov-hmf/#k_x-0.4"},"372":{"title":"Two-stream Instability","pagetitle":"Vlasov-HMF","ref":"/vlasov-solvers/dev/vlasov-hmf/#Two-stream-Instability"},"373":{"title":"$k_x=0.2, v_0=1.3$","pagetitle":"Vlasov-HMF","ref":"/vlasov-solvers/dev/vlasov-hmf/#k_x0.2,-v_01.3"},"374":{"title":"$k_x = 0.2, v_0 = 3.0$","pagetitle":"Vlasov-HMF","ref":"/vlasov-solvers/dev/vlasov-hmf/#k_x-0.2,-v_0-3.0"},"375":{"title":"Conclusion","pagetitle":"Vlasov-HMF","ref":"/vlasov-solvers/dev/vlasov-hmf/#Conclusion"},"378":{"title":"One Reduced Scalar Spin Vlasov-Maxwell","pagetitle":"One Reduced Scalar Spin Vlasov-Maxwell","ref":"/scalar-spin/dev/#One-Reduced-Scalar-Spin-Vlasov-Maxwell"},"379":{"title":"Spin Vlasov-Maxwell equations","pagetitle":"One Reduced Scalar Spin Vlasov-Maxwell","ref":"/scalar-spin/dev/#Spin-Vlasov-Maxwell-equations"},"380":{"title":"Vlasov equation","pagetitle":"One Reduced Scalar Spin Vlasov-Maxwell","ref":"/scalar-spin/dev/#vlasov"},"381":{"title":"Hamiltonian splitting method","pagetitle":"One Reduced Scalar Spin Vlasov-Maxwell","ref":"/scalar-spin/dev/#Hamiltonian-splitting-method"},"382":{"title":"Reduced spin Vlasov-Maxwell equations","pagetitle":"One Reduced Scalar Spin Vlasov-Maxwell","ref":"/scalar-spin/dev/#Reduced-spin-Vlasov-Maxwell-equations"},"383":{"title":"GEMPIC framework applied to reduced spin Vlasov system.","pagetitle":"One Reduced Scalar Spin Vlasov-Maxwell","ref":"/scalar-spin/dev/#GEMPIC-framework-applied-to-reduced-spin-Vlasov-system."},"384":{"title":"B-splines","pagetitle":"One Reduced Scalar Spin Vlasov-Maxwell","ref":"/scalar-spin/dev/#B-splines"},"385":{"title":"Notations","pagetitle":"One Reduced Scalar Spin Vlasov-Maxwell","ref":"/scalar-spin/dev/#Notations"},"386":{"title":"Discretization of the functional derivatives","pagetitle":"One Reduced Scalar Spin Vlasov-Maxwell","ref":"/scalar-spin/dev/#Discretization-of-the-functional-derivatives"},"387":{"title":"Discrete Poisson bracket","pagetitle":"One Reduced Scalar Spin Vlasov-Maxwell","ref":"/scalar-spin/dev/#Discrete-Poisson-bracket"},"388":{"title":"References","pagetitle":"One Reduced Scalar Spin Vlasov-Maxwell","ref":"/scalar-spin/dev/#References"},"391":{"title":"Contents","pagetitle":"Contents","ref":"/scalar-spin/dev/contents/#Contents"},"392":{"title":"Index","pagetitle":"Contents","ref":"/scalar-spin/dev/contents/#Index"},"395":{"title":"Diagnostics","pagetitle":"Diagnostics","ref":"/scalar-spin/dev/diagnostics/#Diagnostics"},"396":{"title":"SpinGEMPIC.TimeHistoryDiagnostics","pagetitle":"Diagnostics","ref":"/scalar-spin/dev/diagnostics/#SpinGEMPIC.TimeHistoryDiagnostics"},"397":{"title":"SpinGEMPIC.pic_diagnostics_transfer","pagetitle":"Diagnostics","ref":"/scalar-spin/dev/diagnostics/#SpinGEMPIC.pic_diagnostics_transfer-NTuple{4, Any}"},"398":{"title":"SpinGEMPIC.solve_poisson!","pagetitle":"Diagnostics","ref":"/scalar-spin/dev/diagnostics/#SpinGEMPIC.solve_poisson!-Tuple{Vector{Float64}, ParticleGroup, ParticleMeshCoupling, GEMPIC.Maxwell1DFEM, Vector{Float64}}"},"401":{"title":"Distributions","pagetitle":"Distributions","ref":"/scalar-spin/dev/distributions/#Distributions"},"402":{"title":"SpinGEMPIC.CosGaussianParams","pagetitle":"Distributions","ref":"/scalar-spin/dev/distributions/#SpinGEMPIC.CosGaussianParams"},"403":{"title":"SpinGEMPIC.CosSumGaussian","pagetitle":"Distributions","ref":"/scalar-spin/dev/distributions/#SpinGEMPIC.CosSumGaussian"},"404":{"title":"SpinGEMPIC.eval_v_density","pagetitle":"Distributions","ref":"/scalar-spin/dev/distributions/#SpinGEMPIC.eval_v_density-Tuple{SpinGEMPIC.AbstractCosGaussian, Union{Float64, Vector{Float64}}}"},"405":{"title":"SpinGEMPIC.eval_x_density","pagetitle":"Distributions","ref":"/scalar-spin/dev/distributions/#SpinGEMPIC.eval_x_density-Tuple{CosSumGaussian, Union{Float64, Vector{Float64}}}"},"408":{"title":"Paper example","pagetitle":"Paper example","ref":"/scalar-spin/dev/example/#Paper-example"},"411":{"title":"Hamiltonian splitting","pagetitle":"Hamiltonian splitting","ref":"/scalar-spin/dev/hamiltonian_splitting/#Hamiltonian-splitting"},"412":{"title":"SpinGEMPIC.HamiltonianSplitting","pagetitle":"Hamiltonian splitting","ref":"/scalar-spin/dev/hamiltonian_splitting/#SpinGEMPIC.HamiltonianSplitting"},"413":{"title":"SpinGEMPIC.strang_splitting!","pagetitle":"Hamiltonian splitting","ref":"/scalar-spin/dev/hamiltonian_splitting/#SpinGEMPIC.strang_splitting!-Tuple{HamiltonianSplitting, ParticleGroup, Float64, Int64}"},"414":{"title":"Subsystem corresponding to  $H_p$","pagetitle":"Hamiltonian splitting","ref":"/scalar-spin/dev/hamiltonian_splitting/#Subsystem-corresponding-to-H_p"},"415":{"title":"SpinGEMPIC.operatorHp","pagetitle":"Hamiltonian splitting","ref":"/scalar-spin/dev/hamiltonian_splitting/#SpinGEMPIC.operatorHp"},"416":{"title":"Subsystem corresponding to  $H_A$","pagetitle":"Hamiltonian splitting","ref":"/scalar-spin/dev/hamiltonian_splitting/#Subsystem-corresponding-to-H_A"},"417":{"title":"SpinGEMPIC.operatorHA","pagetitle":"Hamiltonian splitting","ref":"/scalar-spin/dev/hamiltonian_splitting/#SpinGEMPIC.operatorHA"},"418":{"title":"Subsystem corresponding to  $H_s$","pagetitle":"Hamiltonian splitting","ref":"/scalar-spin/dev/hamiltonian_splitting/#Subsystem-corresponding-to-H_s"},"419":{"title":"SpinGEMPIC.operatorHs","pagetitle":"Hamiltonian splitting","ref":"/scalar-spin/dev/hamiltonian_splitting/#SpinGEMPIC.operatorHs"},"420":{"title":"Subsystem corresponding to  $H_E$","pagetitle":"Hamiltonian splitting","ref":"/scalar-spin/dev/hamiltonian_splitting/#Subsystem-corresponding-to-H_E"},"421":{"title":"SpinGEMPIC.operatorHE","pagetitle":"Hamiltonian splitting","ref":"/scalar-spin/dev/hamiltonian_splitting/#SpinGEMPIC.operatorHE"},"424":{"title":"Particle group","pagetitle":"Particle group","ref":"/scalar-spin/dev/particle_group/#Particle-group"},"425":{"title":"SpinGEMPIC.ParticleGroup","pagetitle":"Particle group","ref":"/scalar-spin/dev/particle_group/#SpinGEMPIC.ParticleGroup"},"426":{"title":"SpinGEMPIC.get_charge","pagetitle":"Particle group","ref":"/scalar-spin/dev/particle_group/#SpinGEMPIC.get_charge-Tuple{ParticleGroup, Int64}"},"427":{"title":"SpinGEMPIC.get_mass","pagetitle":"Particle group","ref":"/scalar-spin/dev/particle_group/#SpinGEMPIC.get_mass-Tuple{ParticleGroup, Int64}"},"428":{"title":"SpinGEMPIC.get_s1","pagetitle":"Particle group","ref":"/scalar-spin/dev/particle_group/#SpinGEMPIC.get_s1-Tuple{ParticleGroup, Int64}"},"429":{"title":"SpinGEMPIC.get_s2","pagetitle":"Particle group","ref":"/scalar-spin/dev/particle_group/#SpinGEMPIC.get_s2-Tuple{ParticleGroup, Int64}"},"430":{"title":"SpinGEMPIC.get_s3","pagetitle":"Particle group","ref":"/scalar-spin/dev/particle_group/#SpinGEMPIC.get_s3-Tuple{ParticleGroup, Int64}"},"431":{"title":"SpinGEMPIC.get_v","pagetitle":"Particle group","ref":"/scalar-spin/dev/particle_group/#SpinGEMPIC.get_v-Tuple{ParticleGroup, Int64}"},"432":{"title":"SpinGEMPIC.get_weights","pagetitle":"Particle group","ref":"/scalar-spin/dev/particle_group/#SpinGEMPIC.get_weights-Tuple{ParticleGroup, Int64}"},"433":{"title":"SpinGEMPIC.get_x","pagetitle":"Particle group","ref":"/scalar-spin/dev/particle_group/#SpinGEMPIC.get_x-Tuple{ParticleGroup, Int64}"},"434":{"title":"SpinGEMPIC.set_common_weight","pagetitle":"Particle group","ref":"/scalar-spin/dev/particle_group/#SpinGEMPIC.set_common_weight-Tuple{SpinGEMPIC.AbstractParticleGroup, Float64}"},"435":{"title":"SpinGEMPIC.set_s1","pagetitle":"Particle group","ref":"/scalar-spin/dev/particle_group/#SpinGEMPIC.set_s1-Tuple{ParticleGroup, Int64, Float64}"},"436":{"title":"SpinGEMPIC.set_s2","pagetitle":"Particle group","ref":"/scalar-spin/dev/particle_group/#SpinGEMPIC.set_s2-Tuple{ParticleGroup, Int64, Float64}"},"437":{"title":"SpinGEMPIC.set_s3","pagetitle":"Particle group","ref":"/scalar-spin/dev/particle_group/#SpinGEMPIC.set_s3-Tuple{ParticleGroup, Int64, Float64}"},"438":{"title":"SpinGEMPIC.set_v","pagetitle":"Particle group","ref":"/scalar-spin/dev/particle_group/#SpinGEMPIC.set_v-Tuple{ParticleGroup, Int64, Float64}"},"439":{"title":"SpinGEMPIC.set_weights","pagetitle":"Particle group","ref":"/scalar-spin/dev/particle_group/#SpinGEMPIC.set_weights-Tuple{ParticleGroup, Int64, Float64}"},"440":{"title":"SpinGEMPIC.set_x","pagetitle":"Particle group","ref":"/scalar-spin/dev/particle_group/#SpinGEMPIC.set_x-Tuple{ParticleGroup, Int64, Float64}"},"443":{"title":"Particle-Mesh coupling","pagetitle":"Particle-Mesh coupling","ref":"/scalar-spin/dev/particle_mesh_coupling/#Particle-Mesh-coupling"},"444":{"title":"SpinGEMPIC.ParticleMeshCoupling","pagetitle":"Particle-Mesh coupling","ref":"/scalar-spin/dev/particle_mesh_coupling/#SpinGEMPIC.ParticleMeshCoupling"},"445":{"title":"SpinGEMPIC.add_charge!","pagetitle":"Particle-Mesh coupling","ref":"/scalar-spin/dev/particle_mesh_coupling/#SpinGEMPIC.add_charge!-Tuple{Vector{Float64}, ParticleMeshCoupling, Float64, Float64}"},"446":{"title":"SpinGEMPIC.add_current_update_v!","pagetitle":"Particle-Mesh coupling","ref":"/scalar-spin/dev/particle_mesh_coupling/#SpinGEMPIC.add_current_update_v!-Tuple{AbstractArray, ParticleMeshCoupling, Float64, Float64, Float64, Float64, Float64}"},"447":{"title":"SpinGEMPIC.evaluate","pagetitle":"Particle-Mesh coupling","ref":"/scalar-spin/dev/particle_mesh_coupling/#SpinGEMPIC.evaluate-Tuple{ParticleMeshCoupling, Float64, Vector{Float64}}"},"448":{"title":"SpinGEMPIC.update_jv!","pagetitle":"Particle-Mesh coupling","ref":"/scalar-spin/dev/particle_mesh_coupling/#SpinGEMPIC.update_jv!-Tuple{AbstractArray, ParticleMeshCoupling, Float64, Float64, Int64, Float64, Float64, Float64, Float64}"},"451":{"title":"Particle sampling","pagetitle":"Particle sampling","ref":"/scalar-spin/dev/particle_sampling/#Particle-sampling"},"452":{"title":"SpinGEMPIC.sample!","pagetitle":"Particle sampling","ref":"/scalar-spin/dev/particle_sampling/#SpinGEMPIC.sample!-Tuple{Any, Any, SpinGEMPIC.AbstractCosGaussian, Any}"},"453":{"title":"SpinGEMPIC.sample_quietstart!","pagetitle":"Particle sampling","ref":"/scalar-spin/dev/particle_sampling/#SpinGEMPIC.sample_quietstart!-NTuple{4, Any}"},"454":{"title":"SpinGEMPIC.sample_weighted!","pagetitle":"Particle sampling","ref":"/scalar-spin/dev/particle_sampling/#SpinGEMPIC.sample_weighted!-NTuple{4, Any}"},"457":{"title":"Quickstart","pagetitle":"Quickstart","ref":"/scalar-spin/dev/quickstart/#Quickstart"},"458":{"title":"Import packages","pagetitle":"Quickstart","ref":"/scalar-spin/dev/quickstart/#Import-packages"},"459":{"title":"Physics parameters","pagetitle":"Quickstart","ref":"/scalar-spin/dev/quickstart/#Physics-parameters"},"460":{"title":"Initialize mesh","pagetitle":"Quickstart","ref":"/scalar-spin/dev/quickstart/#Initialize-mesh"},"461":{"title":"Initialize particles","pagetitle":"Quickstart","ref":"/scalar-spin/dev/quickstart/#Initialize-particles"},"462":{"title":"Initialize Maxwell solver","pagetitle":"Quickstart","ref":"/scalar-spin/dev/quickstart/#Initialize-Maxwell-solver"},"467":{"title":"VectorSpin","pagetitle":"Home","ref":"/vector-spin/dev/#VectorSpin"},"468":{"title":"Scalar spin laser plasma model","pagetitle":"Home","ref":"/vector-spin/dev/#Scalar-spin-laser-plasma-model"},"471":{"title":"VectorSpin types and functions","pagetitle":"API","ref":"/vector-spin/dev/api/#VectorSpin-types-and-functions"},"472":{"title":"VectorSpin.BSplineAdvection","pagetitle":"API","ref":"/vector-spin/dev/api/#VectorSpin.BSplineAdvection"},"473":{"title":"VectorSpin.Mesh","pagetitle":"API","ref":"/vector-spin/dev/api/#VectorSpin.Mesh"},"474":{"title":"VectorSpin.advection!","pagetitle":"API","ref":"/vector-spin/dev/api/#VectorSpin.advection!-Union{Tuple{T}, Tuple{Any, PSMAdvection{T}, Any, Any}} where T"},"475":{"title":"VectorSpin.bf_energy","pagetitle":"API","ref":"/vector-spin/dev/api/#VectorSpin.bf_energy"},"476":{"title":"VectorSpin.bspline","pagetitle":"API","ref":"/vector-spin/dev/api/#VectorSpin.bspline-Tuple{Any, Any, Any}"},"477":{"title":"VectorSpin.energy","pagetitle":"API","ref":"/vector-spin/dev/api/#VectorSpin.energy-Tuple{Any, Any, Any, Any, Any, Any, Any, Any, Mesh, Any, Any}"},"478":{"title":"VectorSpin.ex_energy","pagetitle":"API","ref":"/vector-spin/dev/api/#VectorSpin.ex_energy-Tuple{Any, Any}"},"479":{"title":"VectorSpin.initialfunction","pagetitle":"API","ref":"/vector-spin/dev/api/#VectorSpin.initialfunction-Union{Tuple{T}, Tuple{Mesh{T}, Vararg{Any, 4}}} where T"},"480":{"title":"VectorSpin.kinetic_energy","pagetitle":"API","ref":"/vector-spin/dev/api/#VectorSpin.kinetic_energy-Tuple{Any, Mesh}"},"481":{"title":"VectorSpin.s_energy","pagetitle":"API","ref":"/vector-spin/dev/api/#VectorSpin.s_energy"},"482":{"title":"VectorSpin.smod","pagetitle":"API","ref":"/vector-spin/dev/api/#VectorSpin.smod-Tuple{Any}"},"483":{"title":"VectorSpin.snorm","pagetitle":"API","ref":"/vector-spin/dev/api/#VectorSpin.snorm-Tuple{Any, Any, Any}"},"484":{"title":"VectorSpin.step!","pagetitle":"API","ref":"/vector-spin/dev/api/#VectorSpin.step!-Union{Tuple{T}, Tuple{H1fhSubsystem{T}, Matrix{T}, Matrix{T}, Matrix{T}, Matrix{T}, Vector{T}, Vector{T}, Vector{T}, T, Any}} where T"},"485":{"title":"VectorSpin.step!","pagetitle":"API","ref":"/vector-spin/dev/api/#VectorSpin.step!-Union{Tuple{T}, Tuple{H2Subsystem{T}, Matrix{T}, Matrix{T}, Matrix{T}, Matrix{T}, Array{Complex{T}, 1}, Array{Complex{T}, 1}, T, Any}} where T"},"486":{"title":"VectorSpin.step!","pagetitle":"API","ref":"/vector-spin/dev/api/#VectorSpin.step!-Union{Tuple{T}, Tuple{H2fhSubsystem{T}, Matrix{T}, Matrix{T}, Matrix{T}, Matrix{T}, Vector{T}, Vector{T}, Vector{T}, T, Any}} where T"},"487":{"title":"VectorSpin.step!","pagetitle":"API","ref":"/vector-spin/dev/api/#VectorSpin.step!-Union{Tuple{T}, Tuple{H3Subsystem{T}, Matrix{T}, Matrix{T}, Matrix{T}, Matrix{T}, Array{Complex{T}, 1}, Array{Complex{T}, 1}, T, Any}} where T"},"488":{"title":"VectorSpin.step!","pagetitle":"API","ref":"/vector-spin/dev/api/#VectorSpin.step!-Union{Tuple{T}, Tuple{H3fhSubsystem{T}, Matrix{T}, Matrix{T}, Matrix{T}, Matrix{T}, Vector{T}, Vector{T}, Vector{T}, T, Any}} where T"},"489":{"title":"VectorSpin.step!","pagetitle":"API","ref":"/vector-spin/dev/api/#VectorSpin.step!-Union{Tuple{T}, Tuple{HASubsystem{T}, Matrix{T}, Matrix{T}, Matrix{T}, Matrix{T}, Array{Complex{T}, 1}, Array{Complex{T}, 1}, Array{Complex{T}, 1}, Array{Complex{T}, 1}, T}} where T"},"490":{"title":"VectorSpin.step!","pagetitle":"API","ref":"/vector-spin/dev/api/#VectorSpin.step!-Union{Tuple{T}, Tuple{HeSubsystem{T}, Matrix{T}, Matrix{T}, Matrix{T}, Matrix{T}, Array{Complex{T}, 1}, Array{Complex{T}, 1}, Array{Complex{T}, 1}, Array{Complex{T}, 1}, Array{Complex{T}, 1}, T}} where T"},"491":{"title":"VectorSpin.step!","pagetitle":"API","ref":"/vector-spin/dev/api/#VectorSpin.step!-Union{Tuple{T}, Tuple{HpSubsystem{T}, Matrix{T}, Matrix{T}, Matrix{T}, Matrix{T}, Array{Complex{T}, 1}, T}} where T"},"492":{"title":"VectorSpin.step!","pagetitle":"API","ref":"/vector-spin/dev/api/#VectorSpin.step!-Union{Tuple{T}, Tuple{HvSubsystem{T}, Matrix{T}, Matrix{T}, Matrix{T}, Matrix{T}, Array{Complex{T}, 1}, T}} where T"},"495":{"title":"Example","pagetitle":"Vlasov-Maxwell","ref":"/vector-spin/dev/example/#Example"},"498":{"title":"Hamiltonian splitting","pagetitle":"Hamiltonian Splitting","ref":"/vector-spin/dev/hamiltonian_splitting/#Hamiltonian-splitting"},"499":{"title":"Subsystem for  $\\mathcal{H}_p$","pagetitle":"Hamiltonian Splitting","ref":"/vector-spin/dev/hamiltonian_splitting/#Subsystem-for-\\\\mathcal{H}_p"},"500":{"title":"Subsystem for  $\\mathcal{H}_A$","pagetitle":"Hamiltonian Splitting","ref":"/vector-spin/dev/hamiltonian_splitting/#Subsystem-for-\\\\mathcal{H}_A"},"501":{"title":"Subsystem for  $\\mathcal{H}_E$","pagetitle":"Hamiltonian Splitting","ref":"/vector-spin/dev/hamiltonian_splitting/#Subsystem-for-\\\\mathcal{H}_E"},"502":{"title":"Subsystem for  $\\mathcal{H}_2$","pagetitle":"Hamiltonian Splitting","ref":"/vector-spin/dev/hamiltonian_splitting/#Subsystem-for-\\\\mathcal{H}_2"},"503":{"title":"Subsystem for  $\\mathcal{H}_3$","pagetitle":"Hamiltonian Splitting","ref":"/vector-spin/dev/hamiltonian_splitting/#Subsystem-for-\\\\mathcal{H}_3"},"506":{"title":"Numerical scheme","pagetitle":"Numerical scheme","ref":"/vector-spin/dev/numerical_scheme/#Numerical-scheme"},"509":{"title":"Model with ions and spin effects","pagetitle":"Version with ions","ref":"/vector-spin/dev/spin_ions/#Model-with-ions-and-spin-effects"},"512":{"title":"Stimulated Raman Scattering without spin","pagetitle":"Validation","ref":"/vector-spin/dev/srs_without_spin/#Stimulated-Raman-Scattering-without-spin"}}